{ "frames": {
   "Chibi-character-template_skin3_part1_by_AxulArt #running_down 0.aseprite": {
    "frame": { "x": 0, "y": 0, "w": 32, "h": 32 },
    "rotated": false,
    "trimmed": false,
    "spriteSourceSize": { "x": 0, "y": 0, "w": 32, "h": 32 },
    "sourceSize": { "w": 32, "h": 32 },
    "duration": 100
   },
   "Chibi-character-template_skin3_part1_by_AxulArt #running_down 1.aseprite": {
    "frame": { "x": 32, "y": 0, "w": 32, "h": 32 },
    "rotated": false,
    "trimmed": false,
    "spriteSourceSize": { "x": 0, "y": 0, "w": 32, "h": 32 },
    "sourceSize": { "w": 32, "h": 32 },
    "duration": 100
   },
   "Chibi-character-template_skin3_part1_by_AxulArt #running_down 2.aseprite": {
    "frame": { "x": 64, "y": 0, "w": 32, "h": 32 },
    "rotated": false,
    "trimmed": false,
    "spriteSourceSize": { "x": 0, "y": 0, "w": 32, "h": 32 },
    "sourceSize": { "w": 32, "h": 32 },
    "duration": 100
   },
   "Chibi-character-template_skin3_part1_by_AxulArt #running_down 3.aseprite": {
    "frame": { "x": 96, "y": 0, "w": 32, "h": 32 },
    "rotated": false,
    "trimmed": false,
    "spriteSourceSize": { "x": 0, "y": 0, "w": 32, "h": 32 },
    "sourceSize": { "w": 32, "h": 32 },
    "duration": 100
   },
   "Chibi-character-template_skin3_part1_by_AxulArt #running_down 4.aseprite": {
    "frame": { "x": 128, "y": 0, "w": 32, "h": 32 },
    "rotated": false,
    "trimmed": false,
    "spriteSourceSize": { "x": 0, "y": 0, "w": 32, "h": 32 },
    "sourceSize": { "w": 32, "h": 32 },
    "duration": 100
   },
   "Chibi-character-template_skin3_part1_by_AxulArt #running_down 5.aseprite": {
    "frame": { "x": 160, "y": 0, "w": 32, "h": 32 },
    "rotated": false,
    "trimmed": false,
    "spriteSourceSize": { "x": 0, "y": 0, "w": 32, "h": 32 },
    "sourceSize": { "w": 32, "h": 32 },
    "duration": 100
   },
   "Chibi-character-template_skin3_part1_by_AxulArt #running_down 6.aseprite": {
    "frame": { "x": 192, "y": 0, "w": 32, "h": 32 },
    "rotated": false,
    "trimmed": false,
    "spriteSourceSize": { "x": 0, "y": 0, "w": 32, "h": 32 },
    "sourceSize": { "w": 32, "h": 32 },
    "duration": 100
   },
   "Chibi-character-template_skin3_part1_by_AxulArt #running_down 7.aseprite": {
    "frame": { "x": 224, "y": 0, "w": 32, "h": 32 },
    "rotated": false,
    "trimmed": false,
    "spriteSourceSize": { "x": 0, "y": 0, "w": 32, "h": 32 },
    "sourceSize": { "w": 32, "h": 32 },
    "duration": 100
   },
   "Chibi-character-template_skin3_part1_by_AxulArt #running_down 8.aseprite": {
    "frame": { "x": 256, "y": 0, "w": 32, "h": 32 },
    "rotated": false,
    "trimmed": false,
    "spriteSourceSize": { "x": 0, "y": 0, "w": 32, "h": 32 },
    "sourceSize": { "w": 32, "h": 32 },
    "duration": 100
   },
   "Chibi-character-template_skin3_part1_by_AxulArt #running_down 9.aseprite": {
    "frame": { "x": 288, "y": 0, "w": 32, "h": 32 },
    "rotated": false,
    "trimmed": false,
    "spriteSourceSize": { "x": 0, "y": 0, "w": 32, "h": 32 },
    "sourceSize": { "w": 32, "h": 32 },
    "duration": 100
   },
   "Chibi-character-template_skin3_part1_by_AxulArt #running_down 10.aseprite": {
    "frame": { "x": 0, "y": 32, "w": 32, "h": 32 },
    "rotated": false,
    "trimmed": false,
    "spriteSourceSize": { "x": 0, "y": 0, "w": 32, "h": 32 },
    "sourceSize": { "w": 32, "h": 32 },
    "duration": 100
   },
   "Chibi-character-template_skin3_part1_by_AxulArt #running_down 11.aseprite": {
    "frame": { "x": 32, "y": 32, "w": 32, "h": 32 },
    "rotated": false,
    "trimmed": false,
    "spriteSourceSize": { "x": 0, "y": 0, "w": 32, "h": 32 },
    "sourceSize": { "w": 32, "h": 32 },
    "duration": 100
   },
   "Chibi-character-template_skin3_part1_by_AxulArt #running_left 0.aseprite": {
    "frame": { "x": 64, "y": 32, "w": 32, "h": 32 },
    "rotated": false,
    "trimmed": false,
    "spriteSourceSize": { "x": 0, "y": 0, "w": 32, "h": 32 },
    "sourceSize": { "w": 32, "h": 32 },
    "duration": 100
   },
   "Chibi-character-template_skin3_part1_by_AxulArt #running_left 1.aseprite": {
    "frame": { "x": 96, "y": 32, "w": 32, "h": 32 },
    "rotated": false,
    "trimmed": false,
    "spriteSourceSize": { "x": 0, "y": 0, "w": 32, "h": 32 },
    "sourceSize": { "w": 32, "h": 32 },
    "duration": 100
   },
   "Chibi-character-template_skin3_part1_by_AxulArt #running_left 2.aseprite": {
    "frame": { "x": 128, "y": 32, "w": 32, "h": 32 },
    "rotated": false,
    "trimmed": false,
    "spriteSourceSize": { "x": 0, "y": 0, "w": 32, "h": 32 },
    "sourceSize": { "w": 32, "h": 32 },
    "duration": 100
   },
   "Chibi-character-template_skin3_part1_by_AxulArt #running_left 3.aseprite": {
    "frame": { "x": 160, "y": 32, "w": 32, "h": 32 },
    "rotated": false,
    "trimmed": false,
    "spriteSourceSize": { "x": 0, "y": 0, "w": 32, "h": 32 },
    "sourceSize": { "w": 32, "h": 32 },
    "duration": 100
   },
   "Chibi-character-template_skin3_part1_by_AxulArt #running_left 4.aseprite": {
    "frame": { "x": 192, "y": 32, "w": 32, "h": 32 },
    "rotated": false,
    "trimmed": false,
    "spriteSourceSize": { "x": 0, "y": 0, "w": 32, "h": 32 },
    "sourceSize": { "w": 32, "h": 32 },
    "duration": 100
   },
   "Chibi-character-template_skin3_part1_by_AxulArt #running_left 5.aseprite": {
    "frame": { "x": 224, "y": 32, "w": 32, "h": 32 },
    "rotated": false,
    "trimmed": false,
    "spriteSourceSize": { "x": 0, "y": 0, "w": 32, "h": 32 },
    "sourceSize": { "w": 32, "h": 32 },
    "duration": 100
   },
   "Chibi-character-template_skin3_part1_by_AxulArt #running_left 6.aseprite": {
    "frame": { "x": 256, "y": 32, "w": 32, "h": 32 },
    "rotated": false,
    "trimmed": false,
    "spriteSourceSize": { "x": 0, "y": 0, "w": 32, "h": 32 },
    "sourceSize": { "w": 32, "h": 32 },
    "duration": 100
   },
   "Chibi-character-template_skin3_part1_by_AxulArt #running_left 7.aseprite": {
    "frame": { "x": 288, "y": 32, "w": 32, "h": 32 },
    "rotated": false,
    "trimmed": false,
    "spriteSourceSize": { "x": 0, "y": 0, "w": 32, "h": 32 },
    "sourceSize": { "w": 32, "h": 32 },
    "duration": 100
   },
   "Chibi-character-template_skin3_part1_by_AxulArt #running_left 8.aseprite": {
    "frame": { "x": 0, "y": 64, "w": 32, "h": 32 },
    "rotated": false,
    "trimmed": false,
    "spriteSourceSize": { "x": 0, "y": 0, "w": 32, "h": 32 },
    "sourceSize": { "w": 32, "h": 32 },
    "duration": 100
   },
   "Chibi-character-template_skin3_part1_by_AxulArt #running_left 9.aseprite": {
    "frame": { "x": 32, "y": 64, "w": 32, "h": 32 },
    "rotated": false,
    "trimmed": false,
    "spriteSourceSize": { "x": 0, "y": 0, "w": 32, "h": 32 },
    "sourceSize": { "w": 32, "h": 32 },
    "duration": 100
   },
   "Chibi-character-template_skin3_part1_by_AxulArt #running_left 10.aseprite": {
    "frame": { "x": 64, "y": 64, "w": 32, "h": 32 },
    "rotated": false,
    "trimmed": false,
    "spriteSourceSize": { "x": 0, "y": 0, "w": 32, "h": 32 },
    "sourceSize": { "w": 32, "h": 32 },
    "duration": 100
   },
   "Chibi-character-template_skin3_part1_by_AxulArt #running_left 11.aseprite": {
    "frame": { "x": 96, "y": 64, "w": 32, "h": 32 },
    "rotated": false,
    "trimmed": false,
    "spriteSourceSize": { "x": 0, "y": 0, "w": 32, "h": 32 },
    "sourceSize": { "w": 32, "h": 32 },
    "duration": 100
   },
   "Chibi-character-template_skin3_part1_by_AxulArt #running_right 0.aseprite": {
    "frame": { "x": 128, "y": 64, "w": 32, "h": 32 },
    "rotated": false,
    "trimmed": false,
    "spriteSourceSize": { "x": 0, "y": 0, "w": 32, "h": 32 },
    "sourceSize": { "w": 32, "h": 32 },
    "duration": 100
   },
   "Chibi-character-template_skin3_part1_by_AxulArt #running_right 1.aseprite": {
    "frame": { "x": 160, "y": 64, "w": 32, "h": 32 },
    "rotated": false,
    "trimmed": false,
    "spriteSourceSize": { "x": 0, "y": 0, "w": 32, "h": 32 },
    "sourceSize": { "w": 32, "h": 32 },
    "duration": 100
   },
   "Chibi-character-template_skin3_part1_by_AxulArt #running_right 2.aseprite": {
    "frame": { "x": 192, "y": 64, "w": 32, "h": 32 },
    "rotated": false,
    "trimmed": false,
    "spriteSourceSize": { "x": 0, "y": 0, "w": 32, "h": 32 },
    "sourceSize": { "w": 32, "h": 32 },
    "duration": 100
   },
   "Chibi-character-template_skin3_part1_by_AxulArt #running_right 3.aseprite": {
    "frame": { "x": 224, "y": 64, "w": 32, "h": 32 },
    "rotated": false,
    "trimmed": false,
    "spriteSourceSize": { "x": 0, "y": 0, "w": 32, "h": 32 },
    "sourceSize": { "w": 32, "h": 32 },
    "duration": 100
   },
   "Chibi-character-template_skin3_part1_by_AxulArt #running_right 4.aseprite": {
    "frame": { "x": 256, "y": 64, "w": 32, "h": 32 },
    "rotated": false,
    "trimmed": false,
    "spriteSourceSize": { "x": 0, "y": 0, "w": 32, "h": 32 },
    "sourceSize": { "w": 32, "h": 32 },
    "duration": 100
   },
   "Chibi-character-template_skin3_part1_by_AxulArt #running_right 5.aseprite": {
    "frame": { "x": 288, "y": 64, "w": 32, "h": 32 },
    "rotated": false,
    "trimmed": false,
    "spriteSourceSize": { "x": 0, "y": 0, "w": 32, "h": 32 },
    "sourceSize": { "w": 32, "h": 32 },
    "duration": 100
   },
   "Chibi-character-template_skin3_part1_by_AxulArt #running_right 6.aseprite": {
    "frame": { "x": 0, "y": 96, "w": 32, "h": 32 },
    "rotated": false,
    "trimmed": false,
    "spriteSourceSize": { "x": 0, "y": 0, "w": 32, "h": 32 },
    "sourceSize": { "w": 32, "h": 32 },
    "duration": 100
   },
   "Chibi-character-template_skin3_part1_by_AxulArt #running_right 7.aseprite": {
    "frame": { "x": 32, "y": 96, "w": 32, "h": 32 },
    "rotated": false,
    "trimmed": false,
    "spriteSourceSize": { "x": 0, "y": 0, "w": 32, "h": 32 },
    "sourceSize": { "w": 32, "h": 32 },
    "duration": 100
   },
   "Chibi-character-template_skin3_part1_by_AxulArt #running_right 8.aseprite": {
    "frame": { "x": 64, "y": 96, "w": 32, "h": 32 },
    "rotated": false,
    "trimmed": false,
    "spriteSourceSize": { "x": 0, "y": 0, "w": 32, "h": 32 },
    "sourceSize": { "w": 32, "h": 32 },
    "duration": 100
   },
   "Chibi-character-template_skin3_part1_by_AxulArt #running_right 9.aseprite": {
    "frame": { "x": 96, "y": 96, "w": 32, "h": 32 },
    "rotated": false,
    "trimmed": false,
    "spriteSourceSize": { "x": 0, "y": 0, "w": 32, "h": 32 },
    "sourceSize": { "w": 32, "h": 32 },
    "duration": 100
   },
   "Chibi-character-template_skin3_part1_by_AxulArt #running_right 10.aseprite": {
    "frame": { "x": 128, "y": 96, "w": 32, "h": 32 },
    "rotated": false,
    "trimmed": false,
    "spriteSourceSize": { "x": 0, "y": 0, "w": 32, "h": 32 },
    "sourceSize": { "w": 32, "h": 32 },
    "duration": 100
   },
   "Chibi-character-template_skin3_part1_by_AxulArt #running_right 11.aseprite": {
    "frame": { "x": 160, "y": 96, "w": 32, "h": 32 },
    "rotated": false,
    "trimmed": false,
    "spriteSourceSize": { "x": 0, "y": 0, "w": 32, "h": 32 },
    "sourceSize": { "w": 32, "h": 32 },
    "duration": 100
   },
   "Chibi-character-template_skin3_part1_by_AxulArt #running_up 0.aseprite": {
    "frame": { "x": 192, "y": 96, "w": 32, "h": 32 },
    "rotated": false,
    "trimmed": false,
    "spriteSourceSize": { "x": 0, "y": 0, "w": 32, "h": 32 },
    "sourceSize": { "w": 32, "h": 32 },
    "duration": 100
   },
   "Chibi-character-template_skin3_part1_by_AxulArt #running_up 1.aseprite": {
    "frame": { "x": 224, "y": 96, "w": 32, "h": 32 },
    "rotated": false,
    "trimmed": false,
    "spriteSourceSize": { "x": 0, "y": 0, "w": 32, "h": 32 },
    "sourceSize": { "w": 32, "h": 32 },
    "duration": 100
   },
   "Chibi-character-template_skin3_part1_by_AxulArt #running_up 2.aseprite": {
    "frame": { "x": 256, "y": 96, "w": 32, "h": 32 },
    "rotated": false,
    "trimmed": false,
    "spriteSourceSize": { "x": 0, "y": 0, "w": 32, "h": 32 },
    "sourceSize": { "w": 32, "h": 32 },
    "duration": 100
   },
   "Chibi-character-template_skin3_part1_by_AxulArt #running_up 3.aseprite": {
    "frame": { "x": 288, "y": 96, "w": 32, "h": 32 },
    "rotated": false,
    "trimmed": false,
    "spriteSourceSize": { "x": 0, "y": 0, "w": 32, "h": 32 },
    "sourceSize": { "w": 32, "h": 32 },
    "duration": 100
   },
   "Chibi-character-template_skin3_part1_by_AxulArt #running_up 4.aseprite": {
    "frame": { "x": 0, "y": 128, "w": 32, "h": 32 },
    "rotated": false,
    "trimmed": false,
    "spriteSourceSize": { "x": 0, "y": 0, "w": 32, "h": 32 },
    "sourceSize": { "w": 32, "h": 32 },
    "duration": 100
   },
   "Chibi-character-template_skin3_part1_by_AxulArt #running_up 5.aseprite": {
    "frame": { "x": 32, "y": 128, "w": 32, "h": 32 },
    "rotated": false,
    "trimmed": false,
    "spriteSourceSize": { "x": 0, "y": 0, "w": 32, "h": 32 },
    "sourceSize": { "w": 32, "h": 32 },
    "duration": 100
   },
   "Chibi-character-template_skin3_part1_by_AxulArt #running_up 6.aseprite": {
    "frame": { "x": 64, "y": 128, "w": 32, "h": 32 },
    "rotated": false,
    "trimmed": false,
    "spriteSourceSize": { "x": 0, "y": 0, "w": 32, "h": 32 },
    "sourceSize": { "w": 32, "h": 32 },
    "duration": 100
   },
   "Chibi-character-template_skin3_part1_by_AxulArt #running_up 7.aseprite": {
    "frame": { "x": 96, "y": 128, "w": 32, "h": 32 },
    "rotated": false,
    "trimmed": false,
    "spriteSourceSize": { "x": 0, "y": 0, "w": 32, "h": 32 },
    "sourceSize": { "w": 32, "h": 32 },
    "duration": 100
   },
   "Chibi-character-template_skin3_part1_by_AxulArt #running_up 8.aseprite": {
    "frame": { "x": 128, "y": 128, "w": 32, "h": 32 },
    "rotated": false,
    "trimmed": false,
    "spriteSourceSize": { "x": 0, "y": 0, "w": 32, "h": 32 },
    "sourceSize": { "w": 32, "h": 32 },
    "duration": 100
   },
   "Chibi-character-template_skin3_part1_by_AxulArt #running_up 9.aseprite": {
    "frame": { "x": 160, "y": 128, "w": 32, "h": 32 },
    "rotated": false,
    "trimmed": false,
    "spriteSourceSize": { "x": 0, "y": 0, "w": 32, "h": 32 },
    "sourceSize": { "w": 32, "h": 32 },
    "duration": 100
   },
   "Chibi-character-template_skin3_part1_by_AxulArt #running_up 10.aseprite": {
    "frame": { "x": 192, "y": 128, "w": 32, "h": 32 },
    "rotated": false,
    "trimmed": false,
    "spriteSourceSize": { "x": 0, "y": 0, "w": 32, "h": 32 },
    "sourceSize": { "w": 32, "h": 32 },
    "duration": 100
   },
   "Chibi-character-template_skin3_part1_by_AxulArt #running_up 11.aseprite": {
    "frame": { "x": 224, "y": 128, "w": 32, "h": 32 },
    "rotated": false,
    "trimmed": false,
    "spriteSourceSize": { "x": 0, "y": 0, "w": 32, "h": 32 },
    "sourceSize": { "w": 32, "h": 32 },
    "duration": 100
   },
   "Chibi-character-template_skin3_part1_by_AxulArt #running_downleft 0.aseprite": {
    "frame": { "x": 256, "y": 128, "w": 32, "h": 32 },
    "rotated": false,
    "trimmed": false,
    "spriteSourceSize": { "x": 0, "y": 0, "w": 32, "h": 32 },
    "sourceSize": { "w": 32, "h": 32 },
    "duration": 100
   },
   "Chibi-character-template_skin3_part1_by_AxulArt #running_downleft 1.aseprite": {
    "frame": { "x": 288, "y": 128, "w": 32, "h": 32 },
    "rotated": false,
    "trimmed": false,
    "spriteSourceSize": { "x": 0, "y": 0, "w": 32, "h": 32 },
    "sourceSize": { "w": 32, "h": 32 },
    "duration": 100
   },
   "Chibi-character-template_skin3_part1_by_AxulArt #running_downleft 2.aseprite": {
    "frame": { "x": 0, "y": 160, "w": 32, "h": 32 },
    "rotated": false,
    "trimmed": false,
    "spriteSourceSize": { "x": 0, "y": 0, "w": 32, "h": 32 },
    "sourceSize": { "w": 32, "h": 32 },
    "duration": 100
   },
   "Chibi-character-template_skin3_part1_by_AxulArt #running_downleft 3.aseprite": {
    "frame": { "x": 32, "y": 160, "w": 32, "h": 32 },
    "rotated": false,
    "trimmed": false,
    "spriteSourceSize": { "x": 0, "y": 0, "w": 32, "h": 32 },
    "sourceSize": { "w": 32, "h": 32 },
    "duration": 100
   },
   "Chibi-character-template_skin3_part1_by_AxulArt #running_downleft 4.aseprite": {
    "frame": { "x": 64, "y": 160, "w": 32, "h": 32 },
    "rotated": false,
    "trimmed": false,
    "spriteSourceSize": { "x": 0, "y": 0, "w": 32, "h": 32 },
    "sourceSize": { "w": 32, "h": 32 },
    "duration": 100
   },
   "Chibi-character-template_skin3_part1_by_AxulArt #running_downleft 5.aseprite": {
    "frame": { "x": 96, "y": 160, "w": 32, "h": 32 },
    "rotated": false,
    "trimmed": false,
    "spriteSourceSize": { "x": 0, "y": 0, "w": 32, "h": 32 },
    "sourceSize": { "w": 32, "h": 32 },
    "duration": 100
   },
   "Chibi-character-template_skin3_part1_by_AxulArt #running_downleft 6.aseprite": {
    "frame": { "x": 128, "y": 160, "w": 32, "h": 32 },
    "rotated": false,
    "trimmed": false,
    "spriteSourceSize": { "x": 0, "y": 0, "w": 32, "h": 32 },
    "sourceSize": { "w": 32, "h": 32 },
    "duration": 100
   },
   "Chibi-character-template_skin3_part1_by_AxulArt #running_downleft 7.aseprite": {
    "frame": { "x": 160, "y": 160, "w": 32, "h": 32 },
    "rotated": false,
    "trimmed": false,
    "spriteSourceSize": { "x": 0, "y": 0, "w": 32, "h": 32 },
    "sourceSize": { "w": 32, "h": 32 },
    "duration": 100
   },
   "Chibi-character-template_skin3_part1_by_AxulArt #running_downleft 8.aseprite": {
    "frame": { "x": 192, "y": 160, "w": 32, "h": 32 },
    "rotated": false,
    "trimmed": false,
    "spriteSourceSize": { "x": 0, "y": 0, "w": 32, "h": 32 },
    "sourceSize": { "w": 32, "h": 32 },
    "duration": 100
   },
   "Chibi-character-template_skin3_part1_by_AxulArt #running_downleft 9.aseprite": {
    "frame": { "x": 224, "y": 160, "w": 32, "h": 32 },
    "rotated": false,
    "trimmed": false,
    "spriteSourceSize": { "x": 0, "y": 0, "w": 32, "h": 32 },
    "sourceSize": { "w": 32, "h": 32 },
    "duration": 100
   },
   "Chibi-character-template_skin3_part1_by_AxulArt #running_downleft 10.aseprite": {
    "frame": { "x": 256, "y": 160, "w": 32, "h": 32 },
    "rotated": false,
    "trimmed": false,
    "spriteSourceSize": { "x": 0, "y": 0, "w": 32, "h": 32 },
    "sourceSize": { "w": 32, "h": 32 },
    "duration": 100
   },
   "Chibi-character-template_skin3_part1_by_AxulArt #running_downleft 11.aseprite": {
    "frame": { "x": 288, "y": 160, "w": 32, "h": 32 },
    "rotated": false,
    "trimmed": false,
    "spriteSourceSize": { "x": 0, "y": 0, "w": 32, "h": 32 },
    "sourceSize": { "w": 32, "h": 32 },
    "duration": 100
   },
   "Chibi-character-template_skin3_part1_by_AxulArt #running_downright 0.aseprite": {
    "frame": { "x": 0, "y": 192, "w": 32, "h": 32 },
    "rotated": false,
    "trimmed": false,
    "spriteSourceSize": { "x": 0, "y": 0, "w": 32, "h": 32 },
    "sourceSize": { "w": 32, "h": 32 },
    "duration": 100
   },
   "Chibi-character-template_skin3_part1_by_AxulArt #running_downright 1.aseprite": {
    "frame": { "x": 32, "y": 192, "w": 32, "h": 32 },
    "rotated": false,
    "trimmed": false,
    "spriteSourceSize": { "x": 0, "y": 0, "w": 32, "h": 32 },
    "sourceSize": { "w": 32, "h": 32 },
    "duration": 100
   },
   "Chibi-character-template_skin3_part1_by_AxulArt #running_downright 2.aseprite": {
    "frame": { "x": 64, "y": 192, "w": 32, "h": 32 },
    "rotated": false,
    "trimmed": false,
    "spriteSourceSize": { "x": 0, "y": 0, "w": 32, "h": 32 },
    "sourceSize": { "w": 32, "h": 32 },
    "duration": 100
   },
   "Chibi-character-template_skin3_part1_by_AxulArt #running_downright 3.aseprite": {
    "frame": { "x": 96, "y": 192, "w": 32, "h": 32 },
    "rotated": false,
    "trimmed": false,
    "spriteSourceSize": { "x": 0, "y": 0, "w": 32, "h": 32 },
    "sourceSize": { "w": 32, "h": 32 },
    "duration": 100
   },
   "Chibi-character-template_skin3_part1_by_AxulArt #running_downright 4.aseprite": {
    "frame": { "x": 128, "y": 192, "w": 32, "h": 32 },
    "rotated": false,
    "trimmed": false,
    "spriteSourceSize": { "x": 0, "y": 0, "w": 32, "h": 32 },
    "sourceSize": { "w": 32, "h": 32 },
    "duration": 100
   },
   "Chibi-character-template_skin3_part1_by_AxulArt #running_downright 5.aseprite": {
    "frame": { "x": 160, "y": 192, "w": 32, "h": 32 },
    "rotated": false,
    "trimmed": false,
    "spriteSourceSize": { "x": 0, "y": 0, "w": 32, "h": 32 },
    "sourceSize": { "w": 32, "h": 32 },
    "duration": 100
   },
   "Chibi-character-template_skin3_part1_by_AxulArt #running_downright 6.aseprite": {
    "frame": { "x": 192, "y": 192, "w": 32, "h": 32 },
    "rotated": false,
    "trimmed": false,
    "spriteSourceSize": { "x": 0, "y": 0, "w": 32, "h": 32 },
    "sourceSize": { "w": 32, "h": 32 },
    "duration": 100
   },
   "Chibi-character-template_skin3_part1_by_AxulArt #running_downright 7.aseprite": {
    "frame": { "x": 224, "y": 192, "w": 32, "h": 32 },
    "rotated": false,
    "trimmed": false,
    "spriteSourceSize": { "x": 0, "y": 0, "w": 32, "h": 32 },
    "sourceSize": { "w": 32, "h": 32 },
    "duration": 100
   },
   "Chibi-character-template_skin3_part1_by_AxulArt #running_downright 8.aseprite": {
    "frame": { "x": 256, "y": 192, "w": 32, "h": 32 },
    "rotated": false,
    "trimmed": false,
    "spriteSourceSize": { "x": 0, "y": 0, "w": 32, "h": 32 },
    "sourceSize": { "w": 32, "h": 32 },
    "duration": 100
   },
   "Chibi-character-template_skin3_part1_by_AxulArt #running_downright 9.aseprite": {
    "frame": { "x": 288, "y": 192, "w": 32, "h": 32 },
    "rotated": false,
    "trimmed": false,
    "spriteSourceSize": { "x": 0, "y": 0, "w": 32, "h": 32 },
    "sourceSize": { "w": 32, "h": 32 },
    "duration": 100
   },
   "Chibi-character-template_skin3_part1_by_AxulArt #running_downright 10.aseprite": {
    "frame": { "x": 0, "y": 224, "w": 32, "h": 32 },
    "rotated": false,
    "trimmed": false,
    "spriteSourceSize": { "x": 0, "y": 0, "w": 32, "h": 32 },
    "sourceSize": { "w": 32, "h": 32 },
    "duration": 100
   },
   "Chibi-character-template_skin3_part1_by_AxulArt #running_downright 11.aseprite": {
    "frame": { "x": 32, "y": 224, "w": 32, "h": 32 },
    "rotated": false,
    "trimmed": false,
    "spriteSourceSize": { "x": 0, "y": 0, "w": 32, "h": 32 },
    "sourceSize": { "w": 32, "h": 32 },
    "duration": 100
   },
   "Chibi-character-template_skin3_part1_by_AxulArt #running_topleft 0.aseprite": {
    "frame": { "x": 64, "y": 224, "w": 32, "h": 32 },
    "rotated": false,
    "trimmed": false,
    "spriteSourceSize": { "x": 0, "y": 0, "w": 32, "h": 32 },
    "sourceSize": { "w": 32, "h": 32 },
    "duration": 100
   },
   "Chibi-character-template_skin3_part1_by_AxulArt #running_topleft 1.aseprite": {
    "frame": { "x": 96, "y": 224, "w": 32, "h": 32 },
    "rotated": false,
    "trimmed": false,
    "spriteSourceSize": { "x": 0, "y": 0, "w": 32, "h": 32 },
    "sourceSize": { "w": 32, "h": 32 },
    "duration": 100
   },
   "Chibi-character-template_skin3_part1_by_AxulArt #running_topleft 2.aseprite": {
    "frame": { "x": 128, "y": 224, "w": 32, "h": 32 },
    "rotated": false,
    "trimmed": false,
    "spriteSourceSize": { "x": 0, "y": 0, "w": 32, "h": 32 },
    "sourceSize": { "w": 32, "h": 32 },
    "duration": 100
   },
   "Chibi-character-template_skin3_part1_by_AxulArt #running_topleft 3.aseprite": {
    "frame": { "x": 160, "y": 224, "w": 32, "h": 32 },
    "rotated": false,
    "trimmed": false,
    "spriteSourceSize": { "x": 0, "y": 0, "w": 32, "h": 32 },
    "sourceSize": { "w": 32, "h": 32 },
    "duration": 100
   },
   "Chibi-character-template_skin3_part1_by_AxulArt #running_topleft 4.aseprite": {
    "frame": { "x": 192, "y": 224, "w": 32, "h": 32 },
    "rotated": false,
    "trimmed": false,
    "spriteSourceSize": { "x": 0, "y": 0, "w": 32, "h": 32 },
    "sourceSize": { "w": 32, "h": 32 },
    "duration": 100
   },
   "Chibi-character-template_skin3_part1_by_AxulArt #running_topleft 5.aseprite": {
    "frame": { "x": 224, "y": 224, "w": 32, "h": 32 },
    "rotated": false,
    "trimmed": false,
    "spriteSourceSize": { "x": 0, "y": 0, "w": 32, "h": 32 },
    "sourceSize": { "w": 32, "h": 32 },
    "duration": 100
   },
   "Chibi-character-template_skin3_part1_by_AxulArt #running_topleft 6.aseprite": {
    "frame": { "x": 256, "y": 224, "w": 32, "h": 32 },
    "rotated": false,
    "trimmed": false,
    "spriteSourceSize": { "x": 0, "y": 0, "w": 32, "h": 32 },
    "sourceSize": { "w": 32, "h": 32 },
    "duration": 100
   },
   "Chibi-character-template_skin3_part1_by_AxulArt #running_topleft 7.aseprite": {
    "frame": { "x": 288, "y": 224, "w": 32, "h": 32 },
    "rotated": false,
    "trimmed": false,
    "spriteSourceSize": { "x": 0, "y": 0, "w": 32, "h": 32 },
    "sourceSize": { "w": 32, "h": 32 },
    "duration": 100
   },
   "Chibi-character-template_skin3_part1_by_AxulArt #running_topleft 8.aseprite": {
    "frame": { "x": 0, "y": 256, "w": 32, "h": 32 },
    "rotated": false,
    "trimmed": false,
    "spriteSourceSize": { "x": 0, "y": 0, "w": 32, "h": 32 },
    "sourceSize": { "w": 32, "h": 32 },
    "duration": 100
   },
   "Chibi-character-template_skin3_part1_by_AxulArt #running_topleft 9.aseprite": {
    "frame": { "x": 32, "y": 256, "w": 32, "h": 32 },
    "rotated": false,
    "trimmed": false,
    "spriteSourceSize": { "x": 0, "y": 0, "w": 32, "h": 32 },
    "sourceSize": { "w": 32, "h": 32 },
    "duration": 100
   },
   "Chibi-character-template_skin3_part1_by_AxulArt #running_topleft 10.aseprite": {
    "frame": { "x": 64, "y": 256, "w": 32, "h": 32 },
    "rotated": false,
    "trimmed": false,
    "spriteSourceSize": { "x": 0, "y": 0, "w": 32, "h": 32 },
    "sourceSize": { "w": 32, "h": 32 },
    "duration": 100
   },
   "Chibi-character-template_skin3_part1_by_AxulArt #running_topleft 11.aseprite": {
    "frame": { "x": 96, "y": 256, "w": 32, "h": 32 },
    "rotated": false,
    "trimmed": false,
    "spriteSourceSize": { "x": 0, "y": 0, "w": 32, "h": 32 },
    "sourceSize": { "w": 32, "h": 32 },
    "duration": 100
   },
   "Chibi-character-template_skin3_part1_by_AxulArt #running_topright 0.aseprite": {
    "frame": { "x": 128, "y": 256, "w": 32, "h": 32 },
    "rotated": false,
    "trimmed": false,
    "spriteSourceSize": { "x": 0, "y": 0, "w": 32, "h": 32 },
    "sourceSize": { "w": 32, "h": 32 },
    "duration": 100
   },
   "Chibi-character-template_skin3_part1_by_AxulArt #running_topright 1.aseprite": {
    "frame": { "x": 160, "y": 256, "w": 32, "h": 32 },
    "rotated": false,
    "trimmed": false,
    "spriteSourceSize": { "x": 0, "y": 0, "w": 32, "h": 32 },
    "sourceSize": { "w": 32, "h": 32 },
    "duration": 100
   },
   "Chibi-character-template_skin3_part1_by_AxulArt #running_topright 2.aseprite": {
    "frame": { "x": 192, "y": 256, "w": 32, "h": 32 },
    "rotated": false,
    "trimmed": false,
    "spriteSourceSize": { "x": 0, "y": 0, "w": 32, "h": 32 },
    "sourceSize": { "w": 32, "h": 32 },
    "duration": 100
   },
   "Chibi-character-template_skin3_part1_by_AxulArt #running_topright 3.aseprite": {
    "frame": { "x": 224, "y": 256, "w": 32, "h": 32 },
    "rotated": false,
    "trimmed": false,
    "spriteSourceSize": { "x": 0, "y": 0, "w": 32, "h": 32 },
    "sourceSize": { "w": 32, "h": 32 },
    "duration": 100
   },
   "Chibi-character-template_skin3_part1_by_AxulArt #running_topright 4.aseprite": {
    "frame": { "x": 256, "y": 256, "w": 32, "h": 32 },
    "rotated": false,
    "trimmed": false,
    "spriteSourceSize": { "x": 0, "y": 0, "w": 32, "h": 32 },
    "sourceSize": { "w": 32, "h": 32 },
    "duration": 100
   },
   "Chibi-character-template_skin3_part1_by_AxulArt #running_topright 5.aseprite": {
    "frame": { "x": 288, "y": 256, "w": 32, "h": 32 },
    "rotated": false,
    "trimmed": false,
    "spriteSourceSize": { "x": 0, "y": 0, "w": 32, "h": 32 },
    "sourceSize": { "w": 32, "h": 32 },
    "duration": 100
   },
   "Chibi-character-template_skin3_part1_by_AxulArt #running_topright 6.aseprite": {
    "frame": { "x": 0, "y": 288, "w": 32, "h": 32 },
    "rotated": false,
    "trimmed": false,
    "spriteSourceSize": { "x": 0, "y": 0, "w": 32, "h": 32 },
    "sourceSize": { "w": 32, "h": 32 },
    "duration": 100
   },
   "Chibi-character-template_skin3_part1_by_AxulArt #running_topright 7.aseprite": {
    "frame": { "x": 32, "y": 288, "w": 32, "h": 32 },
    "rotated": false,
    "trimmed": false,
    "spriteSourceSize": { "x": 0, "y": 0, "w": 32, "h": 32 },
    "sourceSize": { "w": 32, "h": 32 },
    "duration": 100
   },
   "Chibi-character-template_skin3_part1_by_AxulArt #running_topright 8.aseprite": {
    "frame": { "x": 64, "y": 288, "w": 32, "h": 32 },
    "rotated": false,
    "trimmed": false,
    "spriteSourceSize": { "x": 0, "y": 0, "w": 32, "h": 32 },
    "sourceSize": { "w": 32, "h": 32 },
    "duration": 100
   },
   "Chibi-character-template_skin3_part1_by_AxulArt #running_topright 9.aseprite": {
    "frame": { "x": 96, "y": 288, "w": 32, "h": 32 },
    "rotated": false,
    "trimmed": false,
    "spriteSourceSize": { "x": 0, "y": 0, "w": 32, "h": 32 },
    "sourceSize": { "w": 32, "h": 32 },
    "duration": 100
   },
   "Chibi-character-template_skin3_part1_by_AxulArt #running_topright 10.aseprite": {
    "frame": { "x": 128, "y": 288, "w": 32, "h": 32 },
    "rotated": false,
    "trimmed": false,
    "spriteSourceSize": { "x": 0, "y": 0, "w": 32, "h": 32 },
    "sourceSize": { "w": 32, "h": 32 },
    "duration": 100
   },
   "Chibi-character-template_skin3_part1_by_AxulArt #running_topright 11.aseprite": {
    "frame": { "x": 160, "y": 288, "w": 32, "h": 32 },
    "rotated": false,
    "trimmed": false,
    "spriteSourceSize": { "x": 0, "y": 0, "w": 32, "h": 32 },
    "sourceSize": { "w": 32, "h": 32 },
    "duration": 100
   }
 },
 "meta": {
  "app": "http://www.aseprite.org/",
  "version": "1.x-dev",
  "image": "Chibi-character-template_skin3_part1_by_AxulArt.png",
  "format": "RGBA8888",
  "size": { "w": 320, "h": 320 },
  "scale": "1",
  "frameTags": [
   { "name": "running_down", "from": 0, "to": 11, "direction": "forward", "color": "#000000ff" },
   { "name": "running_left", "from": 12, "to": 23, "direction": "forward", "color": "#000000ff" },
   { "name": "running_right", "from": 24, "to": 35, "direction": "forward", "color": "#000000ff" },
   { "name": "running_up", "from": 36, "to": 47, "direction": "forward", "color": "#000000ff" },
   { "name": "running_downleft", "from": 48, "to": 59, "direction": "forward", "color": "#000000ff" },
   { "name": "running_downright", "from": 60, "to": 71, "direction": "forward", "color": "#000000ff" },
   { "name": "running_upleft", "from": 72, "to": 83, "direction": "forward", "color": "#000000ff" },
   { "name": "running_upright", "from": 84, "to": 95, "direction": "forward", "color": "#000000ff" }
  ],
  "layers": [
   { "name": "Sprite Sheet", "opacity": 255, "blendMode": "normal" }
  ],
  "slices": [
  ]
 }
}
